CHANGES.txt
COPYRIGHT.txt
LICENSE.txt
MANIFEST.in
README.txt
bootstrap.py
buildout.cfg
setup.py
src/hurry/__init__.py
src/hurry.yui.egg-info/PKG-INFO
src/hurry.yui.egg-info/SOURCES.txt
src/hurry.yui.egg-info/dependency_links.txt
src/hurry.yui.egg-info/entry_points.txt
src/hurry.yui.egg-info/namespace_packages.txt
src/hurry.yui.egg-info/not-zip-safe
src/hurry.yui.egg-info/requires.txt
src/hurry.yui.egg-info/top_level.txt
src/hurry/yui/__init__.py
src/hurry/yui/basic.txt
src/hurry/yui/depend.py
src/hurry/yui/download.py
src/hurry/yui/prepare.py
src/hurry/yui/tests.py
src/hurry/yui/yui.py
src/hurry/yui/yui-build/animation/animation-debug.js
src/hurry/yui/yui-build/animation/animation-min.js
src/hurry/yui/yui-build/animation/animation.js
src/hurry/yui/yui-build/assets/skins/sam/ajax-loader.gif
src/hurry/yui/yui-build/assets/skins/sam/asc.gif
src/hurry/yui/yui-build/assets/skins/sam/autocomplete.css
src/hurry/yui/yui-build/assets/skins/sam/bg-h.gif
src/hurry/yui/yui-build/assets/skins/sam/bg-v.gif
src/hurry/yui/yui-build/assets/skins/sam/blankimage.png
src/hurry/yui/yui-build/assets/skins/sam/button.css
src/hurry/yui/yui-build/assets/skins/sam/calendar.css
src/hurry/yui/yui-build/assets/skins/sam/carousel.css
src/hurry/yui/yui-build/assets/skins/sam/colorpicker.css
src/hurry/yui/yui-build/assets/skins/sam/container.css
src/hurry/yui/yui-build/assets/skins/sam/datatable.css
src/hurry/yui/yui-build/assets/skins/sam/desc.gif
src/hurry/yui/yui-build/assets/skins/sam/dt-arrow-dn.png
src/hurry/yui/yui-build/assets/skins/sam/dt-arrow-up.png
src/hurry/yui/yui-build/assets/skins/sam/editor-knob.gif
src/hurry/yui/yui-build/assets/skins/sam/editor-sprite-active.gif
src/hurry/yui/yui-build/assets/skins/sam/editor-sprite.gif
src/hurry/yui/yui-build/assets/skins/sam/editor.css
src/hurry/yui/yui-build/assets/skins/sam/header_background.png
src/hurry/yui/yui-build/assets/skins/sam/hue_bg.png
src/hurry/yui/yui-build/assets/skins/sam/imagecropper.css
src/hurry/yui/yui-build/assets/skins/sam/layout.css
src/hurry/yui/yui-build/assets/skins/sam/layout_sprite.png
src/hurry/yui/yui-build/assets/skins/sam/loading.gif
src/hurry/yui/yui-build/assets/skins/sam/logger.css
src/hurry/yui/yui-build/assets/skins/sam/menu-button-arrow-disabled.png
