Metadata-Version: 1.0
Name: hurry.yui
Version: 2.7.0.1
Summary: hurry.resource style resources for YUI.
Home-page: UNKNOWN
Author: Martijn Faassen
Author-email: faassen@startifact.com
License: ZPL 2.1
Platform: UNKNOWN
